faust_ctypes/__init__.py
faust_ctypes/dllarch.c
faust_ctypes/ftypes.py
faust_ctypes/interface.py
faust_ctypes/metadata.py
faust_ctypes/processor.py
faust_ctypes/wrapper.py
faust_ctypes-0.1.2.dist-info/METADATA
faust_ctypes-0.1.2.dist-info/WHEEL
faust_ctypes-0.1.2.dist-info/RECORD
