Metadata-Version: 2.1
Name: faust-ctypes
Version: 0.1.2
Summary: a port of Marc Joliet's FaustPy to Ctypes
Author: Antonin Dudermel
Author-email: antonin.dudermel@caramail.fr
Requires-Python: >=3.8
Classifier: Programming Language :: Python :: 3
Classifier: Programming Language :: Python :: 3.8
Classifier: Programming Language :: Python :: 3.9
Classifier: Programming Language :: Python :: 3.10
Classifier: Programming Language :: Python :: 3.11
Requires-Dist: numpy (>=1.18.0)
Project-URL: Documentation, https://adud2.gitlab.io/faust-ctypes/
